.DS_Store
.travis.yml
AUTHORS
ChangeLog
LICENSE
Makefile
README.md
appveyor.yml
requirements.txt
setup.cfg
setup.py
tox.ini
.cache/v/cache/lastfailed
.vscode/settings.json
.vscode/tasks.json
docs/index.md
junc/__init__.py
junc/server.py
junc/storage.py
junc.egg-info/PKG-INFO
junc.egg-info/SOURCES.txt
junc.egg-info/dependency_links.txt
junc.egg-info/entry_points.txt
junc.egg-info/not-zip-safe
junc.egg-info/pbr.json
junc.egg-info/requires.txt
junc.egg-info/top_level.txt
junc/tests/__init__.py
junc/tests/test_junc.py
junc/tests/test_server.py
junc/tests/test_server_list.py
junc/tests/test_storage.py