Metadata-Version: 1.2
Name: junc
Version: 2.1.2
Summary: Connect to servers easily
Home-page: http://github.com/llamicron/junc
Author: llamicron
Author-email: llamicron@gmail.com
License: MIT
Project-URL: Documentation, https://github.com/llamicron/junc/blob/master/docs/index.md
Project-URL: Source Code, http://github.com/llamicron/junc
Keywords: ssh
Platform: UNKNOWN
Classifier: Development Status :: 4 - Beta
Classifier: Environment :: Console
Classifier: Intended Audience :: Developers
Classifier: Intended Audience :: Information Technology
Classifier: Operating System :: OS Independent
Classifier: Programming Language :: Python
